{"title":"  共通基礎科目","syllabus":[{"subject":"線形代数1","url":"http://syllabus.sic.shibaura-it.ac.jp/syllabus/2016/dsn/90110.html?Y00","credit":2},{"subject":"微積分学1","url":"http://syllabus.sic.shibaura-it.ac.jp/syllabus/2016/dsn/90112.html?Y00","credit":2},{"subject":"微積分学1演習","url":"http://syllabus.sic.shibaura-it.ac.jp/syllabus/2016/dsn/90113.html?Y00","credit":1},{"subject":"一般力学1","url":"http://syllabus.sic.shibaura-it.ac.jp/syllabus/2016/dsn/90120.html?Y00","credit":2},{"subject":"化学","url":"http://syllabus.sic.shibaura-it.ac.jp/syllabus/2016/dsn/90124.html?Y00","credit":2},{"subject":"線形代数2","url":"http://syllabus.sic.shibaura-it.ac.jp/syllabus/2016/dsn/90111.html?Y00","credit":2},{"subject":"微積分学2","url":"http://syllabus.sic.shibaura-it.ac.jp/syllabus/2016/dsn/90114.html?Y00","credit":2},{"subject":"微積分学2演習","url":"http://syllabus.sic.shibaura-it.ac.jp/syllabus/2016/dsn/90262.html?Y00","credit":1},{"subject":"微分方程式","url":"http://syllabus.sic.shibaura-it.ac.jp/syllabus/2016/dsn/90115.html?Y00","credit":2},{"subject":"一般力学2","url":"http://syllabus.sic.shibaura-it.ac.jp/syllabus/2016/dsn/90121.html?Y00","credit":2},{"subject":"物理学1","url":"http://syllabus.sic.shibaura-it.ac.jp/syllabus/2016/dsn/90122.html?Y00","credit":2},{"subject":"解析学1","url":"http://syllabus.sic.shibaura-it.ac.jp/syllabus/2016/dsn/90116.html?Y00","credit":2},{"subject":"数値解析","url":"http://syllabus.sic.shibaura-it.ac.jp/syllabus/2016/dsn/90119.html?Y00","credit":2},{"subject":"物理学2","url":"http://syllabus.sic.shibaura-it.ac.jp/syllabus/2016/dsn/90123.html?Y00","credit":2},{"subject":"解析学2","url":"http://syllabus.sic.shibaura-it.ac.jp/syllabus/2016/dsn/90117.html?Y00","credit":2},{"subject":"確率統計","url":"http://syllabus.sic.shibaura-it.ac.jp/syllabus/2016/dsn/90118.html?Y00","credit":2},{"subject":"社会ニーズ調査技法","url":"http://syllabus.sic.shibaura-it.ac.jp/syllabus/2016/dsn/90480.html?Y00","credit":2},{"subject":"情報処理1","url":"http://syllabus.sic.shibaura-it.ac.jp/syllabus/2016/dsn/90125.html?Y00","credit":2},{"subject":"情報処理演習1","url":"http://syllabus.sic.shibaura-it.ac.jp/syllabus/2016/dsn/90126.html?Y00","credit":1},{"subject":"社会ニーズ分析","url":"http://syllabus.sic.shibaura-it.ac.jp/syllabus/2016/dsn/90467.html?Y00","credit":2},{"subject":"情報処理2","url":"http://syllabus.sic.shibaura-it.ac.jp/syllabus/2016/dsn/90127.html?Y00","credit":2},{"subject":"情報処理演習2","url":"http://syllabus.sic.shibaura-it.ac.jp/syllabus/2016/dsn/90128.html?Y00","credit":1},{"subject":"工学システム解析","url":"http://syllabus.sic.shibaura-it.ac.jp/syllabus/2016/dsn/90129.html?Y00","credit":2},{"subject":"数理計画法","url":"http://syllabus.sic.shibaura-it.ac.jp/syllabus/2016/dsn/90130.html?Y00","credit":2},{"subject":"CAD／CG演習","url":"http://syllabus.sic.shibaura-it.ac.jp/syllabus/2016/dsn/90132.html?Y00","credit":2},{"subject":"機械力学","url":"http://syllabus.sic.shibaura-it.ac.jp/syllabus/2016/dsn/90133.html?Y00","credit":2},{"subject":"構造力学1","url":"http://syllabus.sic.shibaura-it.ac.jp/syllabus/2016/dsn/90134.html?Y00","credit":2},{"subject":"基礎エレクトロニクス","url":"http://syllabus.sic.shibaura-it.ac.jp/syllabus/2016/dsn/90135.html?Y00","credit":2},{"subject":"材料力学","url":"http://syllabus.sic.shibaura-it.ac.jp/syllabus/2016/dsn/90136.html?Y00","credit":2},{"subject":"熱流体基礎","url":"http://syllabus.sic.shibaura-it.ac.jp/syllabus/2016/dsn/90512.html?Y00","credit":2},{"subject":"社会統計解析","url":"http://syllabus.sic.shibaura-it.ac.jp/syllabus/2016/dsn/90478.html?Y00","credit":2},{"subject":"電気機器基礎","url":"http://syllabus.sic.shibaura-it.ac.jp/syllabus/2016/dsn/90131.html?Y00","credit":2},{"subject":"材料科学","url":"http://syllabus.sic.shibaura-it.ac.jp/syllabus/2016/dsn/90137.html?Y00","credit":2},{"subject":"統計学演習","url":"http://syllabus.sic.shibaura-it.ac.jp/syllabus/2016/dsn/90468.html?Y00","credit":2},{"subject":"シミュレーション工学","url":"http://syllabus.sic.shibaura-it.ac.jp/syllabus/2016/dsn/90138.html?Y00","credit":2}]}